gpc/__init__.py
gpc/__main__.py
gpc/change_executors_factory.py
gpc/change_setting.py
gpc/changes_converter.py
gpc/cli.py
gpc/config_validator.py
gpc/executors/__init__.py
gpc/executors/approval_options_executor.py
gpc/executors/approval_rules_executor.py
gpc/executors/approval_settings_executor.py
gpc/executors/approvers_mixin.py
gpc/executors/base_setting_executor.py
gpc/executors/change_executor.py
gpc/executors/deploy_keys_executor.py
gpc/executors/group_setting_executor.py
gpc/executors/jira_setting_executor.py
gpc/executors/label_setting_executor.py
gpc/executors/members_executor.py
gpc/executors/pipelines_email_executor.py
gpc/executors/profile_label_mixin.py
gpc/executors/profile_member_mixin.py
gpc/executors/project_badges.py
gpc/executors/project_setting_executor.py
gpc/executors/properties_updator.py
gpc/executors/protected_branch_setting_executor.py
gpc/executors/protected_tag_setting_executor.py
gpc/executors/push_rules_setting_executor.py
gpc/executors/runners_executor.py
gpc/executors/schedules_executor.py
gpc/executors/variables_setting_executor.py
gpc/general_executor.py
gpc/helpers/__init__.py
gpc/helpers/action_helper.py
gpc/helpers/click_mutually_excl_opt.py
gpc/helpers/error_codes.py
gpc/helpers/exceptions.py
gpc/helpers/gitlab_helper.py
gpc/helpers/graphql_helper.py
gpc/helpers/hider.py
gpc/helpers/mail_reporter.py
gpc/helpers/project_approval.py
gpc/helpers/remerge.py
gpc/helpers/session_helper.py
gpc/helpers/tests/__init__.py
gpc/helpers/tests/test_gitlab_helper.py
gpc/helpers/tests/test_mail_reporter.py
gpc/helpers/tests/test_project_approval.py
gpc/helpers/tests/test_remerge.py
gpc/helpers/types.py
gpc/parameters.py
gpc/project_rule_executor.py
gpc/property_manager.py
gpc/rule_matcher.py
gpc/schema/__init__.py
gpc/schema/config.schema.yaml
gpc/templates/__init__.py
gpc/templates/build_diff.html.j2
gpc/templates/footer.html.j2
gpc/templates/groups.html.j2
gpc/templates/layout.html.j2
gpc/templates/mail/__init__.py
gitlab_project_configurator-6.4.3.dist-info/LICENSE
gitlab_project_configurator-6.4.3.dist-info/METADATA
gitlab_project_configurator-6.4.3.dist-info/WHEEL
gitlab_project_configurator-6.4.3.dist-info/entry_points.txt
gitlab_project_configurator-6.4.3.dist-info/RECORD
